.gitignore
LICENSE
Makefile
README.md
codecov.yml
pyproject.toml
setup.cfg
.github/pull_request_template.md
.github/ISSUE_TEMPLATE/bug_report.md
.github/ISSUE_TEMPLATE/feature_request.md
.github/workflows/coverage.yml
.github/workflows/publish_release.yml
.github/workflows/style.yml
src/orquestra/integrations/cirq/__init__.py
src/orquestra/integrations/cirq/py.typed
src/orquestra/integrations/cirq/conversions/__init__.py
src/orquestra/integrations/cirq/conversions/_circuit_conversions.py
src/orquestra/integrations/cirq/conversions/_cirq_pauli_conversions.py
src/orquestra/integrations/cirq/conversions/_openfermion_conversions.py
src/orquestra/integrations/cirq/decompositions/__init__.py
src/orquestra/integrations/cirq/decompositions/_cirq_decompositions.py
src/orquestra/integrations/cirq/noise/__init__.py
src/orquestra/integrations/cirq/noise/basic.py
src/orquestra/integrations/cirq/simulator/__init__.py
src/orquestra/integrations/cirq/simulator/_base.py
src/orquestra/integrations/cirq/simulator/_cirq_simulator.py
src/orquestra/integrations/cirq/simulator/_qsim_simulator.py
src/orquestra/integrations/custatevec/py.typed
src/orquestra/integrations/custatevec/simulator/__init__.py
src/orquestra/integrations/custatevec/simulator/_custatevec.py
src/orquestra_cirq.egg-info/PKG-INFO
src/orquestra_cirq.egg-info/SOURCES.txt
src/orquestra_cirq.egg-info/dependency_links.txt
src/orquestra_cirq.egg-info/not-zip-safe
src/orquestra_cirq.egg-info/requires.txt
src/orquestra_cirq.egg-info/top_level.txt
subtrees/z_quantum_actions/MANIFEST.in
subtrees/z_quantum_actions/Makefile
subtrees/z_quantum_actions/README.rst
subtrees/z_quantum_actions/pyproject.toml
subtrees/z_quantum_actions/pytest.ini
subtrees/z_quantum_actions/sample_setup.py
subtrees/z_quantum_actions/setup_extras.py
subtrees/z_quantum_actions/variables.mk
subtrees/z_quantum_actions/actions/coverage/action.yml
subtrees/z_quantum_actions/actions/publish-release/action.yml
subtrees/z_quantum_actions/actions/ssh_setup/action.yml
subtrees/z_quantum_actions/actions/style/action.yml
subtrees/z_quantum_actions/bin/get_next_version.py
subtrees/z_quantum_actions/tests/test_get_next_version.py
subtrees/z_quantum_actions/workflow-templates/coverage.yml
