Metadata-Version: 2.1
Name: orquestra-cirq
Version: 0.11.0
Summary: "Orquestra Cirq package"
Home-page: https://github.com/zapatacomputing/orquestra-cirq
Author: Zapata Computing Inc.
Author-email: info@zapatacomputing.com,
License: Apache Software License 2.0
Classifier: Programming Language :: Python :: 3
Classifier: Operating System :: OS Independent
Classifier: License :: OSI Approved :: Apache Software License
Classifier: Topic :: Scientific/Engineering
Requires-Python: !=3.9.7,>=3.9
License-File: LICENSE
Requires-Dist: protobuf<4
Requires-Dist: cirq-core~=1.2.0
Requires-Dist: cirq-google~=1.2.0
Requires-Dist: orquestra-quantum
Requires-Dist: openfermion~=1.5.1
Provides-Extra: qsim
Requires-Dist: qsimcirq~=0.16.3; extra == "qsim"
Provides-Extra: dev
Requires-Dist: orquestra-python-dev; extra == "dev"
Requires-Dist: orquestra-cirq[qsim]; extra == "dev"
